pycsvschema/__init__.py
pycsvschema/checker.py
pycsvschema/defaults.py
pycsvschema/exceptions.py
pycsvschema/schema.json
pycsvschema/utilities.py
pycsvschema/validators/__init__.py
pycsvschema/validators/header_validators.py
pycsvschema/validators/row_validators.py
pycsvschema/validators/types.py
pycsvschema-0.0.6.dist-info/LICENSE
pycsvschema-0.0.6.dist-info/METADATA
pycsvschema-0.0.6.dist-info/WHEEL
pycsvschema-0.0.6.dist-info/top_level.txt
pycsvschema-0.0.6.dist-info/RECORD
