Metadata-Version: 2.1
Name: pycsvschema
Version: 0.0.6
Summary: PyCSVSchema is an implementation of CSV Schema in Python.
Home-page: https://github.com/csv-schema/PyCSVSchema
Author: Guangyang Li
Author-email: mail@guangyangli.com
License: MIT
Keywords: csv schema json jsonschema validation validator
Platform: UNKNOWN
Classifier: Development Status :: 3 - Alpha
Classifier: Intended Audience :: Developers
Classifier: Topic :: Software Development :: Libraries :: Python Modules
Classifier: Intended Audience :: Information Technology
Classifier: License :: OSI Approved :: MIT License
Classifier: Programming Language :: Python :: 3.5
Classifier: Programming Language :: Python :: 3.6
Classifier: Programming Language :: Python :: 3.7
Classifier: Programming Language :: Python :: 3.8
Requires-Dist: jsonschema
Requires-Dist: rfc3986
